_config/config.yaml
_config/plugin/choices.py
_config/plugin/default.py
_config/plugin/display_priority.py
_config/plugin/group.py
_config/plugin/init.py
_config/plugin/options.py
_config/plugin/os.py
_config/plugin/positional.py
_config/plugin/source.py
_config/plugin/subcommands.py
_config/plugin/type.py
_config/plugin/contract/init.py
_log/config.yaml
_log/plugin/console.py
_log/plugin/file.py
_log/plugin/init.py
_log/plugin/noop.py
_log/plugin/test.py
_log/plugin/contract/init.py
_patt/config.yaml
_patt/plugin/inst.py
_pop/file.py
_pop/sub.py
_pop/test.py
_rend/README.rst
_rend/config.yaml
_rend/exc/rend.py
_rend/output/json_out.py
_rend/output/nested.py
_rend/output/pretty.py
_rend/output/raw.py
_rend/output/yaml_out.py
_rend/output/contracts/init.py
_rend/rend/init.py
_rend/rend/jinja.py
_rend/rend/json_file.py
_rend/rend/toml_file.py
_rend/rend/yaml_file.py
_rend/rend/yaml_template.py
_rend/rend/contracts/init.py
_seed/config.yaml
_seed/seed/init.py
_seed/template/plugin/.gitignore
_seed/template/plugin/.gitlab-ci.yml
_seed/template/plugin/.pre-commit-config.yaml
_seed/template/plugin/README.rst.jinja
_seed/template/plugin/copier.yml
_seed/template/plugin/pyproject.toml.jinja
_seed/template/plugin/.github/workflows/ci.yaml
_seed/template/plugin/src/{{name}}/__init__.py.jinja
_seed/template/plugin/src/{{name}}/config.yaml.jinja
_seed/template/plugin/src/{{name}}/plugin/init.py.jinja
_seed/template/plugin/test/conftest.py.jinja
_seed/template/plugin/test/test_init.py.jinja
_seed/template/plugin/test/tpath/README.rst
_seed/template/plugin/test/tpath/mods/config.yaml
_seed/template/plugin/test/tpath/mods/src/init.py
hub/README.rst
hub/__main__.py
hub/config.yaml
hub/plugin/cli.py
hub/plugin/completer.py
hub/plugin/config.py
hub/plugin/console.py
hub/plugin/init.py
hub/plugin/ref.py
pluggable_namespace-2.1.0.dist-info/licenses/LICENSE.txt
pns/__init__.py
pns/_contract.c
pns/_contract.py
pns/_data.c
pns/_data.py
pns/_debug.py
pns/_hub.c
pns/_hub.py
pns/contract.py
pns/data.py
pns/dir.py
pns/hub.py
pns/loop.py
pns/mod.py
pluggable_namespace-2.1.0.dist-info/METADATA
pluggable_namespace-2.1.0.dist-info/WHEEL
pluggable_namespace-2.1.0.dist-info/entry_points.txt
pluggable_namespace-2.1.0.dist-info/top_level.txt
pluggable_namespace-2.1.0.dist-info/RECORD
