Metadata-Version: 2.4
Name: pluggable-namespace
Version: 2.1.0
Summary: Pluggable namespaces
Author-email: Tyler Levy Conde <yonstib@gmail.com>
License: MIT License (with Restriction on Thomas Hatch, CTXOS, and Associates)
Classifier: Operating System :: OS Independent
Classifier: Programming Language :: Python :: 3.11
Classifier: Programming Language :: Python :: 3.12
Classifier: Development Status :: 5 - Production/Stable
Classifier: License :: OSI Approved :: Apache Software License
Requires-Python: >=3.11
License-File: LICENSE.txt
Requires-Dist: aioconsole
Requires-Dist: aiofiles
Requires-Dist: argparse
Requires-Dist: PyYaml
Provides-Extra: console
Requires-Dist: aiomonitor; extra == "console"
Requires-Dist: prompt-toolkit; extra == "console"
Provides-Extra: rend
Requires-Dist: aio-yte; extra == "rend"
Requires-Dist: jinja2; extra == "rend"
Requires-Dist: toml; extra == "rend"
Provides-Extra: seed
Requires-Dist: copier; extra == "seed"
Provides-Extra: test
Requires-Dist: pexpect; extra == "test"
Requires-Dist: pytest; extra == "test"
Requires-Dist: pytest-asyncio; extra == "test"
Requires-Dist: setuptools; extra == "test"
Provides-Extra: full
Requires-Dist: aiomonitor; extra == "full"
Requires-Dist: prompt-toolkit; extra == "full"
Requires-Dist: aio-yte; extra == "full"
Requires-Dist: jinja2; extra == "full"
Requires-Dist: toml; extra == "full"
Requires-Dist: copier; extra == "full"
Requires-Dist: pexpect; extra == "full"
Requires-Dist: pytest; extra == "full"
Requires-Dist: pytest-asyncio; extra == "full"
Requires-Dist: setuptools; extra == "full"
Dynamic: license-file
Dynamic: provides-extra
